<annotation>
	<folder>images</folder>
	<filename>Gato67.jpg</filename>
	<path>C:\Users\Bryan Reyes\Desktop\proyecto\deteccion_objetos\images\Gato67.jpg</path>
	<source>
		<database>Unknown</database>
	</source>
	<size>
		<width>295</width>
		<height>171</height>
		<depth>3</depth>
	</size>
	<segmented>0</segmented>
	<object>
		<name>Gato</name>
		<pose>Unspecified</pose>
		<truncated>0</truncated>
		<difficult>0</difficult>
		<bndbox>
			<xmin>109</xmin>
			<ymin>38</ymin>
			<xmax>239</xmax>
			<ymax>149</ymax>
		</bndbox>
	</object>
</annotation>
