<annotation>
	<folder>images</folder>
	<filename>images (40).jpg</filename>
	<path>C:\Users\Bryan Reyes\Desktop\proyecto\deteccion_objetos\images\images (40).jpg</path>
	<source>
		<database>Unknown</database>
	</source>
	<size>
		<width>242</width>
		<height>208</height>
		<depth>3</depth>
	</size>
	<segmented>0</segmented>
	<object>
		<name>guacamaya</name>
		<pose>Unspecified</pose>
		<truncated>0</truncated>
		<difficult>0</difficult>
		<bndbox>
			<xmin>25</xmin>
			<ymin>26</ymin>
			<xmax>123</xmax>
			<ymax>134</ymax>
		</bndbox>
	</object>
	<object>
		<name>guacamaya</name>
		<pose>Unspecified</pose>
		<truncated>1</truncated>
		<difficult>0</difficult>
		<bndbox>
			<xmin>129</xmin>
			<ymin>44</ymin>
			<xmax>229</xmax>
			<ymax>208</ymax>
		</bndbox>
	</object>
</annotation>
